colorful_style/__init__.py
colorful_style/align.py
colorful_style/animate.py
colorful_style/banner.py
colorful_style/box.py
colorful_style/colorate.py
colorful_style/colors.py
colorful_style/config.py
colorful_style/effects.py
colorful_style/interactive.py
colorful_style/system.py
colorful_style/utils.py
colorful_style-2.0.0.dist-info/licenses/LICENSE
colorful_style-2.0.0.dist-info/METADATA
colorful_style-2.0.0.dist-info/WHEEL
colorful_style-2.0.0.dist-info/entry_points.txt
colorful_style-2.0.0.dist-info/top_level.txt
colorful_style-2.0.0.dist-info/RECORD
