Metadata-Version: 2.4
Name: colorful-style
Version: 2.0.0
Summary: A beautiful and advanced Python library for creating stunning TUI designs with enhanced colors and effects
Home-page: https://github.com/giakietdev/colorful-style
Author: QuangThangCoder
Author-email: quangthangcoder@gmail.com
Project-URL: Bug Reports, https://github.com/giakietdev/colorful-style/issues
Project-URL: Source, https://github.com/giakietdev/colorful-style
Project-URL: Documentation, https://github.com/giakietdev/colorful-style#readme
Keywords: terminal,colors,animations,effects,tui,cli,ascii-art,banners,boxes,interactive
Classifier: Development Status :: 5 - Production/Stable
Classifier: Intended Audience :: Developers
Classifier: License :: OSI Approved :: MIT License
Classifier: Operating System :: OS Independent
Classifier: Programming Language :: Python :: 3
Classifier: Programming Language :: Python :: 3.7
Classifier: Programming Language :: Python :: 3.8
Classifier: Programming Language :: Python :: 3.9
Classifier: Programming Language :: Python :: 3.10
Classifier: Programming Language :: Python :: 3.11
Classifier: Programming Language :: Python :: 3.12
Classifier: Topic :: Software Development :: Libraries :: Python Modules
Classifier: Topic :: Terminals
Classifier: Topic :: Text Processing :: Fonts
Classifier: Topic :: Multimedia :: Graphics
Requires-Python: >=3.7
License-File: LICENSE
Requires-Dist: colorama>=0.4.6
Requires-Dist: termcolor>=2.3.0
Requires-Dist: rich>=13.0.0
Requires-Dist: pyfiglet>=1.0.0
Requires-Dist: art>=6.1
Requires-Dist: blessed>=1.20.0
Requires-Dist: cursor>=1.3.5
Provides-Extra: dev
Requires-Dist: pytest>=7.0.0; extra == "dev"
Requires-Dist: pytest-cov>=4.0.0; extra == "dev"
Requires-Dist: black>=23.0.0; extra == "dev"
Requires-Dist: flake8>=6.0.0; extra == "dev"
Requires-Dist: mypy>=1.0.0; extra == "dev"
Provides-Extra: docs
Requires-Dist: sphinx>=6.0.0; extra == "docs"
Requires-Dist: sphinx-rtd-theme>=1.2.0; extra == "docs"
Dynamic: author
Dynamic: author-email
Dynamic: classifier
Dynamic: description
Dynamic: description-content-type
Dynamic: home-page
Dynamic: keywords
Dynamic: license-file
Dynamic: project-url
Dynamic: provides-extra
Dynamic: requires-dist
Dynamic: requires-python
Dynamic: summary
